whitebox_plugin_map/__init__.py
whitebox_plugin_map/apps.py
whitebox_plugin_map/jsx/Map.jsx
whitebox_plugin_map/jsx/OverlayButtonFollow.jsx
whitebox_plugin_map/jsx/WhiteboxFlightMarker.jsx
whitebox_plugin_map/jsx/stores/map.js
whitebox_plugin_map/jsx/stores/map.test.js
whitebox_plugin_map/jsx/utils/leaflet_patch.js
whitebox_plugin_map/urls.py
whitebox_plugin_map/views.py
whitebox_plugin_map/whitebox_plugin_map.py
whitebox_test_plugin_map/__init__.py
whitebox_test_plugin_map/federation/map.spec.js
whitebox_test_plugin_map/federation/whitebox_marker.spec.js
whitebox_test_plugin_map/test_whitebox_plugin_map.py
whitebox_plugin_map-0.1.24.dist-info/LICENSE
whitebox_plugin_map-0.1.24.dist-info/METADATA
whitebox_plugin_map-0.1.24.dist-info/WHEEL
whitebox_plugin_map-0.1.24.dist-info/entry_points.txt
whitebox_plugin_map-0.1.24.dist-info/RECORD
